pysquale/__init__.py
pysquale/_version.py
pysquale/common/__init__.py
pysquale/common/pipeline.py
pysquale/words/__init__.py
pysquale/words/cleaning.py
pysquale/words/preprocessing.py
pysquale/words/utils.py
pysquale/words/files/abbreviations.txt
pysquale/words/files/ibge_female_names.txt
pysquale/words/files/ibge_male_names.txt
pysquale/words/files/lastnames.txt
pysquale/words/files/punctuation.txt
pysquale/words/files/stopwords.txt
pysquale-0.0.11.dist-info/LICENSE
pysquale-0.0.11.dist-info/METADATA
pysquale-0.0.11.dist-info/WHEEL
pysquale-0.0.11.dist-info/top_level.txt
pysquale-0.0.11.dist-info/RECORD
