Metadata-Version: 2.1
Name: pysquale
Version: 0.0.11
Summary: Useful lib for text processing in Portuguese
Home-page: https://pysquale.readthedocs.io/
Author: Henrique Santana
Author-email: santana@cloudhumans.com
License: UNKNOWN
Project-URL: Bug Tracker, https://github.com/santana-ai/pysquale/issues
Platform: UNKNOWN
Classifier: Programming Language :: Python :: 3
Classifier: Programming Language :: Python :: 3.6
Classifier: Programming Language :: Python :: 3.7
Classifier: Programming Language :: Python :: 3.8
Classifier: Programming Language :: Python :: 3.9
Classifier: License :: OSI Approved :: MIT License
Classifier: Operating System :: OS Independent
Requires-Python: >=3.6
License-File: LICENSE
Requires-Dist: nltk (>=3.7)
